Metadata-Version: 2.4
Name: saboteurs
Version: 0.3.4
Summary: Identify agents impairing success across experiments.
Author: Zulko
License-Expression: MIT
Project-URL: Homepage, https://github.com/Edinburgh-Genome-Foundry/saboteurs
Keywords: statistics,weakest link,DNA,part validation
License-File: LICENCE.txt
Requires-Dist: numpy
Requires-Dist: pandas
Requires-Dist: scipy
Requires-Dist: scikit-learn
Requires-Dist: pdf_reports
Requires-Dist: matplotlib
Requires-Dist: flametree
Dynamic: license-file
